dycow/__init__.py
dycow/__main__.py
dycow/settings.py
dycow/utils.py
dycow-0.1.0.0.data/scripts/dw
dycow-0.1.0.0.data/scripts/dycow
dycow-0.1.0.0.dist-info/LICENSE.txt
dycow-0.1.0.0.dist-info/METADATA
dycow-0.1.0.0.dist-info/WHEEL
dycow-0.1.0.0.dist-info/top_level.txt
dycow-0.1.0.0.dist-info/RECORD
