Metadata-Version: 2.1
Name: dycow
Version: 0.1.0.0
Summary: A tiny web-server app with a configuration file, NO NEED TO CODE
Home-page: https://github.com/sanix-darker/dycow
Author: Sanix-darker
Author-email: s4nixd@gmail.com
License: UNKNOWN
Platform: UNKNOWN
Classifier: Programming Language :: Python :: 3
Classifier: License :: OSI Approved :: MIT License
Classifier: Operating System :: OS Independent
Requires-Python: >=3.6
